{
  "kakao:18294946740114616": [
    {
      "sender": "‮",
      "text": "Emoticon",
      "ts": 1784645594205
    },
    {
      "sender": "Unknown",
      "text": "봇 설정에서 레거시 API 사용이 켜져 있나요?\n- API2 사용이 꺼져 있나요? (레거시 API 사용 옵션이 없을 경우)",
      "ts": 1784657577940
    },
    {
      "sender": "Android R",
      "text": "봇 설정에서 레거시 API 사용이 켜져 있나요?\n- API2 사용이 꺼져 있나요? (레거시 API 사용 옵션이 없을 경우)",
      "ts": 1784657579557
    },
    {
      "sender": "Unknown",
      "text": "레거시 api 켰을 때와 껐을 때 모두 동일하게 답장과 로그 모두 작동하지 않습니다...디버그 룸에서도 마찬가지네요",
      "ts": 1784698181583
    },
    {
      "sender": "사루치",
      "text": "레거시 api 켰을 때와 껐을 때 모두 동일하게 답장과 로그 모두 작동하지 않습니다...디버그 룸에서도 마찬가지네요",
      "ts": 1784698183042
    },
    {
      "sender": "Unknown",
      "text": "대체 뭐가 문제일까요ㅠㅠ",
      "ts": 1784698190045
    },
    {
      "sender": "사루치",
      "text": "대체 뭐가 문제일까요ㅠㅠ",
      "ts": 1784698190483
    },
    {
      "sender": "Unknown",
      "text": "저는 구버전이라",
      "ts": 1784698471410
    },
    {
      "sender": "누군가의 부계",
      "text": "저는 구버전이라",
      "ts": 1784698472619
    },
    {
      "sender": "Unknown",
      "text": "정상작동 되는디",
      "ts": 1784698475775
    },
    {
      "sender": "누군가의 부계",
      "text": "정상작동 되는디",
      "ts": 1784698476996
    },
    {
      "sender": "Unknown",
      "text": "몰?루",
      "ts": 1784698478096
    },
    {
      "sender": "누군가의 부계",
      "text": "몰?루",
      "ts": 1784698478560
    },
    {
      "sender": "Unknown",
      "text": "정확한 버전명 알려주실 수 있을까요?",
      "ts": 1784698500734
    },
    {
      "sender": "사루치",
      "text": "정확한 버전명 알려주실 수 있을까요?",
      "ts": 1784698501548
    },
    {
      "sender": "Unknown",
      "text": "29a에용",
      "ts": 1784698521360
    },
    {
      "sender": "누군가의 부계",
      "text": "29a에용",
      "ts": 1784698522782
    },
    {
      "sender": "Unknown",
      "text": "어라",
      "ts": 1784698533865
    },
    {
      "sender": "사루치",
      "text": "어라",
      "ts": 1784698534566
    },
    {
      "sender": "Unknown",
      "text": "29a로도 해봤는데 저는 안되더라구요....",
      "ts": 1784698544319
    },
    {
      "sender": "사루치",
      "text": "29a로도 해봤는데 저는 안되더라구요....",
      "ts": 1784698545060
    },
    {
      "sender": "Unknown",
      "text": "진짜 왜지",
      "ts": 1784698546643
    },
    {
      "sender": "사루치",
      "text": "진짜 왜지",
      "ts": 1784698547636
    },
    {
      "sender": "Unknown",
      "text": "엥",
      "ts": 1784698548963
    },
    {
      "sender": "누군가의 부계",
      "text": "엥",
      "ts": 1784698551000
    },
    {
      "sender": "Unknown",
      "text": "코드 저것만 딱 카피해서 했는데",
      "ts": 1784698565535
    },
    {
      "sender": "누군가의 부계",
      "text": "코드 저것만 딱 카피해서 했는데",
      "ts": 1784698567190
    },
    {
      "sender": "Unknown",
      "text": "잘되는디",
      "ts": 1784698569903
    },
    {
      "sender": "누군가의 부계",
      "text": "잘되는디",
      "ts": 1784698571820
    },
    {
      "sender": "Unknown",
      "text": "제가 어디선가 설정을 놓친 게 있으려나요....",
      "ts": 1784698584439
    },
    {
      "sender": "사루치",
      "text": "제가 어디선가 설정을 놓친 게 있으려나요....",
      "ts": 1784698584677
    },
    {
      "sender": "Unknown",
      "text": "진짜 다 했는데",
      "ts": 1784698588784
    },
    {
      "sender": "사루치",
      "text": "진짜 다 했는데",
      "ts": 1784698589321
    },
    {
      "sender": "Unknown",
      "text": "사진",
      "ts": 1784698591098
    },
    {
      "sender": "누군가의 부계",
      "text": "Photo",
      "ts": 1784698591392
    },
    {
      "sender": "Unknown",
      "text": "혹시 인터프리터 모드로 쓰시나요?",
      "ts": 1784698605613
    },
    {
      "sender": "사루치",
      "text": "혹시 인터프리터 모드로 쓰시나요?",
      "ts": 1784698606765
    },
    {
      "sender": "Unknown",
      "text": "공용로그 보시는것도 아닐거고",
      "ts": 1784698612021
    },
    {
      "sender": "누군가의 부계",
      "text": "공용로그 보시는것도 아닐거고",
      "ts": 1784698613886
    },
    {
      "sender": "Unknown",
      "text": "1 기본값으로 쓰고있어요",
      "ts": 1784698634680
    },
    {
      "sender": "누군가의 부계",
      "text": "1 기본값으로 쓰고있어요",
      "ts": 1784698635599
    },
    {
      "sender": "누군가의 부계",
      "text": "인터프리터 아님",
      "ts": 1784698638963
    },
    {
      "sender": "Unknown",
      "text": "인터프리터 아님",
      "ts": 1784698639044
    },
    {
      "sender": "Unknown",
      "text": "그렇군요...",
      "ts": 1784698645430
    },
    {
      "sender": "사루치",
      "text": "그렇군요...",
      "ts": 1784698647193
    },
    {
      "sender": "Unknown",
      "text": "뭐지",
      "ts": 1784698698695
    },
    {
      "sender": "‮",
      "text": "뭐지",
      "ts": 1784698700062
    },
    {
      "sender": "Unknown",
      "text": "네이버 지오코더 박살났나",
      "ts": 1784698705101
    },
    {
      "sender": "‮",
      "text": "네이버 지오코더 박살났나",
      "ts": 1784698705702
    },
    {
      "sender": "Unknown",
      "text": "왜 상호명 검색이 안되지",
      "ts": 1784698731860
    },
    {
      "sender": "‮",
      "text": "왜 상호명 검색이 안되지",
      "ts": 1784698732281
    },
    {
      "sender": "Unknown",
      "text": "저렇게 이것저것 해보신분이 컴파일을 안하진 않았을거고ㅋㅋ",
      "ts": 1784698770815
    },
    {
      "sender": "누군가의 부계",
      "text": "저렇게 이것저것 해보신분이 컴파일을 안하진 않았을거고ㅋㅋ",
      "ts": 1784698772634
    },
    {
      "sender": "Unknown",
      "text": "아",
      "ts": 1784698773140
    },
    {
      "sender": "‮",
      "text": "아",
      "ts": 1784698774706
    },
    {
      "sender": "Unknown",
      "text": "애드가드 유블록 이게 문제네",
      "ts": 1784698783615
    },
    {
      "sender": "Unknown",
      "text": "당연하죠ㅋㅋ",
      "ts": 1784698783616
    },
    {
      "sender": "‮",
      "text": "애드가드 유블록 이게 문제네",
      "ts": 1784698785200
    },
    {
      "sender": "사루치",
      "text": "당연하죠ㅋㅋ",
      "ts": 1784698785486
    },
    {
      "sender": "Unknown",
      "text": "디버그룸이면 알림받기 꺼져있어도 되는데",
      "ts": 1784698787982
    },
    {
      "sender": "누군가의 부계",
      "text": "디버그룸이면 알림받기 꺼져있어도 되는데",
      "ts": 1784698789354
    },
    {
      "sender": "Unknown",
      "text": "저도 도통 원인을 모르겠습니다",
      "ts": 1784698800483
    },
    {
      "sender": "사루치",
      "text": "저도 도통 원인을 모르겠습니다",
      "ts": 1784698801132
    },
    {
      "sender": "Unknown",
      "text": "로그만 문제가 아니라 답변도 안오는거니까",
      "ts": 1784698804840
    },
    {
      "sender": "누군가의 부계",
      "text": "로그만 문제가 아니라 답변도 안오는거니까",
      "ts": 1784698806300
    },
    {
      "sender": "누군가의 부계",
      "text": "흠",
      "ts": 1784698807082
    },
    {
      "sender": "Unknown",
      "text": "흠",
      "ts": 1784698807158
    },
    {
      "sender": "Unknown",
      "text": "1년 전쯤에 써본 기억이 있는데",
      "ts": 1784698815586
    },
    {
      "sender": "사루치",
      "text": "1년 전쯤에 써본 기억이 있는데",
      "ts": 1784698815587
    },
    {
      "sender": "Unknown",
      "text": "그따는 됐었거든요???",
      "ts": 1784698821997
    },
    {
      "sender": "사루치",
      "text": "그따는 됐었거든요???",
      "ts": 1784698823798
    },
    {
      "sender": "Unknown",
      "text": "개념 쉽긴 한데",
      "ts": 1784698826375
    },
    {
      "sender": "[AI] Skynet",
      "text": "개념 쉽긴 한데",
      "ts": 1784698827158
    },
    {
      "sender": "Unknown",
      "text": "{\"feedType\":25,\"logId\":3890314449597806593,\"hidden\":true,\"targetRevision\":1}",
      "ts": 1784698830748
    },
    {
      "sender": "Unknown",
      "text": "/날씨 평양",
      "ts": 1784698837140
    },
    {
      "sender": "‮",
      "text": "/날씨 평양",
      "ts": 1784698838259
    },
    {
      "sender": "Unknown",
      "text": "해당 위치를 찾을 수 없어요",
      "ts": 1784698841508
    },
    {
      "sender": "[AI] Skynet",
      "text": "해당 위치를 찾을 수 없어요",
      "ts": 1784698842896
    },
    {
      "sender": "Unknown",
      "text": "스카이넷은 아직 고장나있군",
      "ts": 1784698845870
    },
    {
      "sender": "‮",
      "text": "스카이넷은 아직 고장나있군",
      "ts": 1784698846259
    },
    {
      "sender": "Unknown",
      "text": "지웠다 깔아도 보셨을거고",
      "ts": 1784698862454
    },
    {
      "sender": "누군가의 부계",
      "text": "지웠다 깔아도 보셨을거고",
      "ts": 1784698863101
    },
    {
      "sender": "Unknown",
      "text": "네네",
      "ts": 1784698864770
    },
    {
      "sender": "사루치",
      "text": "네네",
      "ts": 1784698866952
    },
    {
      "sender": "Unknown",
      "text": "폰이 바뀌기는 했는데 그게 문제이려나",
      "ts": 1784698871192
    },
    {
      "sender": "사루치",
      "text": "폰이 바뀌기는 했는데 그게 문제이려나",
      "ts": 1784698872601
    },
    {
      "sender": "Unknown",
      "text": "근데 옛날 폰 쓸때도 후반부에 작동 안됐었던 거 같아요",
      "ts": 1784698889816
    },
    {
      "sender": "사루치",
      "text": "근데 옛날 폰 쓸때도 후반부에 작동 안됐었던 거 같아요",
      "ts": 1784698890723
    },
    {
      "sender": "Unknown",
      "text": "진짜 왜지,,,",
      "ts": 1784698892144
    },
    {
      "sender": "사루치",
      "text": "진짜 왜지,,,",
      "ts": 1784698893877
    },
    {
      "sender": "Unknown",
      "text": "아 나도 지오코더 터진거 해결해야 하는데",
      "ts": 1784698929067
    },
    {
      "sender": "DarkTornado.js",
      "text": "아 나도 지오코더 터진거 해결해야 하는데",
      "ts": 1784698929684
    },
    {
      "sender": "Unknown",
      "text": "채자봇 이야기긴 한데",
      "ts": 1784698939538
    },
    {
      "sender": "DarkTornado.js",
      "text": "채자봇 이야기긴 한데",
      "ts": 1784698940167
    },
    {
      "sender": "Unknown",
      "text": "종종 아무 이유 없이 컴파일하면 무조건 팅기는 경우가 있는데",
      "ts": 1784698956111
    },
    {
      "sender": "DarkTornado.js",
      "text": "종종 아무 이유 없이 컴파일하면 무조건 팅기는 경우가 있는데",
      "ts": 1784698956532
    },
    {
      "sender": "Unknown",
      "text": "재부팅하면 해결되긴 했어요",
      "ts": 1784698960478
    },
    {
      "sender": "DarkTornado.js",
      "text": "재부팅하면 해결되긴 했어요",
      "ts": 1784698962175
    },
    {
      "sender": "Unknown",
      "text": "재부팅 한 번 해보세요",
      "ts": 1784698987211
    },
    {
      "sender": "DarkTornado.js",
      "text": "재부팅 한 번 해보세요",
      "ts": 1784698988250
    }
  ],
  "wechat:26308516478@chatroom": [
    {
      "sender": "wxid_r3zjex7x4mcv32",
      "text": "请问睡着了吗",
      "ts": 1784650986021
    },
    {
      "sender": "wxid_r3zjex7x4mcv32",
      "text": "没事了 这家餐馆关门了 打扰了",
      "ts": 1784651124477
    },
    {
      "sender": "COZE Guest Care",
      "text": "sorry!!",
      "ts": 1784682325468
    }
  ],
  "kakao:301321483004194": [
    {
      "sender": "변이규",
      "text": "서형식80 \n김병구80",
      "ts": 1784688799693
    },
    {
      "sender": "변이규",
      "text": "서형식80 \n김병구80",
      "ts": 1784688801035
    },
    {
      "sender": "변이규",
      "text": "서형식\n01053526897",
      "ts": 1784689007860
    },
    {
      "sender": "변이규",
      "text": "서형식\n01053526897",
      "ts": 1784689008937
    },
    {
      "sender": "변이규",
      "text": "김병구\n01086979114",
      "ts": 1784689036657
    },
    {
      "sender": "변이규",
      "text": "김병구\n01086979114",
      "ts": 1784689038537
    }
  ],
  "kakao:474751444159250": [
    {
      "sender": "PetitAmourFlower",
      "text": "안녕하세요.\n숙소 정확한 주소와 공항 픽업 방법 알려주세요",
      "ts": 1784692528235
    },
    {
      "sender": "PetitAmourFlower",
      "text": "안녕하세요.\n숙소 정확한 주소와 공항 픽업 방법 알려주세요",
      "ts": 1784692528563
    },
    {
      "sender": "PetitAmourFlower",
      "text": "2일종도 부모님이 오가실 수 있어요. 괜찮나요?",
      "ts": 1784692557352
    },
    {
      "sender": "PetitAmourFlower",
      "text": "2일종도 부모님이 오가실 수 있어요. 괜찮나요?",
      "ts": 1784692559419
    },
    {
      "sender": "GAYA | GUEST CARE",
      "text": "안녕하세요! 현주 @PetitAmourFlower 님! \n위 정보 열람 부탁드리겠습니다 ^^",
      "ts": 1784692575975
    },
    {
      "sender": "GAYA | GUEST CARE",
      "text": "안녕하세요! 현주 @PetitAmourFlower 님! \n위 정보 열람 부탁드리겠습니다 ^^",
      "ts": 1784692576309
    },
    {
      "sender": "GAYA | GUEST CARE",
      "text": "네 그럼요 ^^",
      "ts": 1784692584400
    },
    {
      "sender": "GAYA | GUEST CARE",
      "text": "네 그럼요 ^^",
      "ts": 1784692586331
    },
    {
      "sender": "GAYA | GUEST CARE",
      "text": "부모님도 해당 톡방 초대주시면 주차 방법등 다 같이 안내드릴게요!",
      "ts": 1784692598925
    },
    {
      "sender": "GAYA | GUEST CARE",
      "text": "부모님도 해당 톡방 초대주시면 주차 방법등 다 같이 안내드릴게요!",
      "ts": 1784692600442
    },
    {
      "sender": "PetitAmourFlower",
      "text": "[공지] 서울특별시 성북구 성북동 178-60",
      "ts": 1784692639864
    },
    {
      "sender": "PetitAmourFlower",
      "text": "Announcement in Boards: 서울특별시 성북구 성북동 178-60",
      "ts": 1784692640632
    },
    {
      "sender": "GAYA | GUEST CARE",
      "text": "🚐📚 공항 밴 이용 완전 가이드북\n\n1️⃣ 예약 방법\n\n• 여행 날짜 / 도착 시간 / 항공사 / 항공편명(Flight No.)을 알려주세요.\n• 확인 후, 픽업 상세 안내 + 기사님 연락처를 보내드립니다.\n\n2️⃣ 밴 서비스 요금 & 프로모션\n\n🎁 프로모션\n• 4박 투숙 → 7인승 밴 1회 FREE\n• 8박 투숙 → 7인승 밴 2회 FREE\n\n💰 추가 요금\n• 김포공항 ↔ 숙소 — 🚗 4인승 ₩70,000 / 🚐 7인승 ₩90,000\n• 인천공항 ↔ 숙소 — 🚗 4인승 ₩100,000 / 🚐 7인승 ₩120,000\n• 서울 시내 짐 운송 — 🚗/🚐 정액 ₩60,000\n\n🛋️ 편안한 이동 팁\n7인 + 짐이 함께라면 7인승 차량이 다소 타이트할 수 있어요. 더 여유롭게 이동하시려면 4인승 2대를 예약하시는 것을 추천드립니다. 😌\n\n3️⃣ 기사님 미팅 안내\n• 기사님이 항공편을 실시간으로 추적하고, 도착 게이트에서 \"성함 피켓\"을 들고 기다립니다.\n• ⏳ 대기 시간: 착륙 후 최대 60분까지 가능합니다.\n• 🤝 기사님을 만나시면 바로 차량으로 이동해 주시면 됩니다.\n💡 추가 서비스 비용(필수 안내)\n• 환전/유심(SIM) 안내: ₩10,000\n• 심야/조조 운행(21:00–06:00): ₩20,000\n• 베이비 카시트: 좌석당 ₩20,000\n• 터미널 간 이동: ₩30,000",
      "ts": 1784692666592
    },
    {
      "sender": "GAYA | GUEST CARE",
      "text": "🚐📚 공항 밴 이용 완전 가이드북\n\n1️⃣ 예약 방법\n\n• 여행 날짜 / 도착 시간 / 항공사 / 항공편명(Flight No.)을 알려주세요.\n• 확인 후, 픽업 상세 안내 + 기사님 연락처를 보내드립니다.\n\n2️⃣ 밴 서비스 요금 & 프로모션\n\n🎁 프로모션\n• 4박 투숙 → 7인승 밴 1회 FREE\n• 8박 투숙 → 7인승 밴 2회 FREE\n\n💰 추가 요금\n• 김포공항 ↔ 숙소 — 🚗 4인승 ₩70,000 / 🚐 7인승 ₩90,000\n• 인천공항 ↔ 숙소 — 🚗 4인승 ₩100,000 / 🚐 7인승 ₩120,000\n• 서울 시내 짐 운송 — 🚗/🚐 정액 ₩60,000\n\n🛋️ 편안한 이동 팁\n7인 + 짐이 함께라면 7인승 차량이 다소 타이트할 수 있어요. 더 여유롭게 이동하시려면 4인승 2대를 예약하시는 것을 추천드립니다. 😌\n\n3️⃣ 기사님 미팅 안내\n• 기사님이 항공편을 실시간으로 추적하고, 도착 게이트에서 \"성함 피켓\"을 들고 기다립니다.\n• ⏳ 대기 시간",
      "ts": 1784692668472
    },
    {
      "sender": "PetitAmourFlower",
      "text": "저희는 4명이라 괜찮아요. 짐은 갈 때는 거의 없어요^^ 아시겠지만",
      "ts": 1784692729984
    },
    {
      "sender": "PetitAmourFlower",
      "text": "저희는 4명이라 괜찮아요. 짐은 갈 때는 거의 없어요^^ 아시겠지만",
      "ts": 1784692731558
    },
    {
      "sender": "GAYA | GUEST CARE",
      "text": "네네!",
      "ts": 1784692746574
    },
    {
      "sender": "GAYA | GUEST CARE",
      "text": "네네!",
      "ts": 1784692747955
    },
    {
      "sender": "PetitAmourFlower",
      "text": "제가 오늘중으로 알려드릴께요",
      "ts": 1784692791634
    },
    {
      "sender": "PetitAmourFlower",
      "text": "제가 오늘중으로 알려드릴께요",
      "ts": 1784692792434
    },
    {
      "sender": "GAYA | GUEST CARE",
      "text": "넵!",
      "ts": 1784692798036
    },
    {
      "sender": "GAYA | GUEST CARE",
      "text": "넵!",
      "ts": 1784692799141
    }
  ]
}